{
  "include": [
    "../../src/python/**/*",
    "../**/*",
    "../../tests/**/*",
    "../../util/**/*",
    "../../ext/pybind11/**/*",
    "./**/*"
  ],
  "exclude": [
    "**/build/**",
    "**/build-*/**",
    "**/.git/**",
    "**/node_modules/**",
    "**/__pycache__/**",
    "**/*.pyc"
  ],
  "extraPaths": [
    "../../src/python",
    "../..",
    "../../util",
    "../../build/X86/python",
    "../../build/ARM/python",
    "../../build/RISCV/python"
  ],
  "pythonVersion": "3.8",
  "pythonPlatform": "Linux",
  "typeCheckingMode": "basic",
  "useLibraryCodeForTypes": true,
  "strictListInference": false,
  "strictDictionaryInference": false,
  "strictSetInference": false,
  "reportMissingImports": "none",
  "reportMissingModuleSource": "none",
  "reportMissingTypeStubs": "none",
  "reportImportCycles": "none",
  "reportUnusedImport": "information",
  "reportUnusedClass": "information",
  "reportUnusedFunction": "information",
  "reportUnusedVariable": "information",
  "reportDuplicateImport": "warning",
  "reportWildcardImportFromLibrary": "warning",
  "reportOptionalSubscript": "none",
  "reportOptionalMemberAccess": "none",
  "reportOptionalCall": "none",
  "reportOptionalIterable": "none",
  "reportOptionalContextManager": "none",
  "reportOptionalOperand": "none",
  "reportUntypedFunctionDecorator": "none",
  "reportUntypedClassDecorator": "none",
  "reportUntypedBaseClass": "none",
  "reportUntypedNamedTuple": "none",
  "reportPrivateUsage": "none",
  "reportConstantRedefinition": "none",
  "reportIncompatibleMethodOverride": "warning",
  "reportIncompatibleVariableOverride": "warning",
  "reportUndefinedVariable": "none",
  "reportAttributeAccessIssue": "none",
  "reportUnknownMemberType": "none",
  "reportUnknownVariableType": "none",
  "reportUnknownArgumentType": "none",
}
